furbox/__init__.py
furbox/main.py
furbox/connectors/__init__.py
furbox/connectors/cache.py
furbox/connectors/downloader.py
furbox/connectors/e621.py
furbox/helpers/__init__.py
furbox/helpers/custom_comic.py
furbox/helpers/e621_comic.py
furbox/helpers/utils.py
furbox/models/__init__.py
furbox/models/config.py
furbox/models/dataclass.py
furbox/models/e621.py
furbox/runners/__init__.py
furbox/runners/cli.py
furbox/runners/comics.py
furbox/runners/e621.py
furbox/utils/__init__.py
furbox/utils/console.py
furbox/utils/progress_bar.py
furbox-0.1.dist-info/LICENSE
furbox-0.1.dist-info/METADATA
furbox-0.1.dist-info/WHEEL
furbox-0.1.dist-info/entry_points.txt
furbox-0.1.dist-info/top_level.txt
furbox-0.1.dist-info/RECORD
